examples/__init__.py
examples/abort.py
examples/bash.py
examples/branching.py
examples/chunking_dag.py
examples/data_store.py
examples/decision.py
examples/multi_data.py
examples/parallel.py
examples/parameters.py
examples/queues.py
examples/sequence.py
examples/simple.py
examples/stop.py
examples/sub_dag.py
examples/timing.py
lightflow/__init__.py
lightflow/config.py
lightflow/logger.py
lightflow/version.py
lightflow/workers.py
lightflow/workflows.py
lightflow/models/__init__.py
lightflow/models/action.py
lightflow/models/dag.py
lightflow/models/dag_signal.py
lightflow/models/datastore.py
lightflow/models/exceptions.py
lightflow/models/mongo_proxy.py
lightflow/models/parameters.py
lightflow/models/signal.py
lightflow/models/task.py
lightflow/models/task_context.py
lightflow/models/task_data.py
lightflow/models/task_parameters.py
lightflow/models/task_signal.py
lightflow/models/utils.py
lightflow/models/workflow.py
lightflow/queue/__init__.py
lightflow/queue/app.py
lightflow/queue/const.py
lightflow/queue/event.py
lightflow/queue/jobs.py
lightflow/queue/models.py
lightflow/queue/pickle.py
lightflow/queue/worker.py
lightflow/scripts/__init__.py
lightflow/scripts/cli.py
lightflow/tasks/__init__.py
lightflow/tasks/bash_task.py
lightflow/tasks/python_task.py
Lightflow-1.11.1.dist-info/LICENSE
Lightflow-1.11.1.dist-info/METADATA
Lightflow-1.11.1.dist-info/WHEEL
Lightflow-1.11.1.dist-info/entry_points.txt
Lightflow-1.11.1.dist-info/top_level.txt
Lightflow-1.11.1.dist-info/RECORD
